Workbook

Sheet Cost Inputs
A1: myTrack — Cost Inputs
A2: Track it. Protect it. myTrack. | EDIT the yellow cells with YOUR real costs. All values below are illustrative placeholders, not real prices.
A4: A. HARDWARE — once-off cost per item | B4: Cost (R) | C4: Notes
A5: Teltonika FMB GPS tracker | B5: 1200 | C5: Core unit fitted to every vehicle
A6: CAN adapter (LV-CAN200) | B6: 1800 | C6: For CAN-bus fuel/ECU data
A7: OBD harness / plug | B7: 350 | C7: Alternative to CAN on light vehicles
A8: LLS fuel probe (fallback) | B8: 2200 | C8: Tank probe for non-CAN vehicles
A9: Panic button | B9: 180 | C9: Driver duress alert
A10: Immobiliser / relay cut-off | B10: 450 | C10: Remote engine disable
A11: RFID / iButton driver ID | B11: 320 | C11: Driver identification
A12: Temperature sensor (reefer) | B12: 650 | C12: Cold-chain monitoring
A13: Backup battery | B13: 280 | C13: Survives main-power tamper
A14: SIM card (once-off) | B14: 50 | C14: Connectivity SIM provisioning
A15: Harness / cabling / consumables | B15: 150 | C15: Fitting consumables per vehicle
A17: B. INSTALLATION & INITIATION
A18: Install labour — Basic (plug & play) /vehicle | B18: 250 | C18: OBD plug, no wiring
A19: Install labour — Standard (wired + CAN) /vehicle | B19: 650 | C19: Hard-wired + CAN tap
A20: Install labour — Advanced (probe + calibration) /vehicle | B20: 1400 | C20: Tank probe + calibration
A21: Auto-electrician call-out /visit | B21: 450 | C21: Per site visit if required
A22: Travel cost /km | B22: 8 | C22: Mobile install / remote sites
A23: Account initiation fee (per account) | B23: 3500 | C23: Platform setup, geofences, users, data load, training
A25: C. MONTHLY RUN COST — per unit / month
A26: SIM / data | B26: 35 | C26: Recurring connectivity
A27: Platform hosting allocation | B27: 18 | C27: Server / Azure share per unit
A28: Software licence | B28: 25 | C28: Per-vehicle platform licence
A29: Support & maintenance reserve | B29: 20 | C29: Helpdesk + field support
A30: Notifications (WhatsApp / SMS) | B30: 12 | C30: Driver & alert messaging
A31: Map / routing API allocation | B31: 8 | C31: Map tiles / speed limits / routing
A32: Warranty / replacement reserve | B32: 15 | C32: Hardware failure provision
A34: D. PRICING LEVERS
A35: Target gross margin % (on monthly run cost) | B35: 0.45 | C35: Markup applied to monthly cost
A36: Hardware markup % | B36: 0.3 | C36: Margin applied to hardware cost
A37: Installation markup % | B37: 0.2 | C37: Margin applied to install labour
A38: Default contract term (months) | B38: 36 | C38: Used as default in Quote Builder
A39: Volume discount — Small (5–20 units) % | B39: 0 | C39: Applied to monthly price
A40: Volume discount — Medium (21–100 units) % | B40: 0.08 | C40: Applied to monthly price
A41: Volume discount — Enterprise (100+ units) % | B41: 0.15 | C41: Applied to monthly price

Sheet Quote Builder
A1: myTrack — Quote Builder
A2: Enter your prospect's fleet below (yellow = your inputs). Green cells pull from Cost Inputs. Everything else is calculated.
A3: Hardware billing: | B3: Amortised | D3: Contract term (months): | F3: =+'Cost Inputs'!B38
A4: Total units: | B4: =SUM(B7:B12) | D4: Fleet tier: | F4: =IF(B4=0,"-",IF(B4<=20,"Small",IF(B4<=100,"Medium","Enterprise"))) | H4: Volume discount applied: | K4: =IF(B4<=20,'Cost Inputs'!B39,IF(B4<=100,'Cost Inputs'!B40,'Cost Inputs'!B41))
A6: Vehicle group | B6: Qty | C6: Data source | D6: Panic | E6: Immobiliser | F6: RFID | G6: Temp sensor | H6: Backup batt | I6: Install level | J6: HW cost/unit | K6: Install cost/unit | L6: HW price/unit | M6: Install price/unit | N6: Run cost/unit/mo | O6: Monthly price/unit | P6: Disc % | Q6: Monthly /unit (final) | R6: Once-off/unit | S6: Line once-off | T6: Line monthly
A7: Long-haul trucks | B7: 12 | C7: CAN | D7: Y | E7: Y | F7: Y | G7: N | H7: Y | I7: Standard | J7: =IF(B7=0,0,'Cost Inputs'!$B$5+'Cost Inputs'!$B$14+'Cost Inputs'!$B$15+IF(C7="CAN",'Cost Inputs'!$B$6,IF(C7="OBD",'Cost Inputs'!$B$7,IF(C7="Probe",'Cost Inputs'!$B$8,0)))+IF(D7="Y",'Cost Inputs'!$B$9,0)+IF(E7="Y",'Cost Inputs'!$B$10,0)+IF(F7="Y",'Cost Inputs'!$B$11,0)+IF(G7="Y",'Cost Inputs'!$B$12,0)+IF(H7="Y",'Cost Inputs'!$B$13,0)) | K7: =IF(I7="Basic",'Cost Inputs'!$B$18,IF(I7="Standard",'Cost Inputs'!$B$19,IF(I7="Advanced",'Cost Inputs'!$B$20,0))) | L7: =J7*(1+'Cost Inputs'!$B$36) | M7: =K7*(1+'Cost Inputs'!$B$37) | N7: =SUM('Cost Inputs'!$B$26:$B$32) | O7: =N7/(1-'Cost Inputs'!$B$35)+IF($B$3="Amortised",L7/$F$3,0) | P7: =$K$4 | Q7: =O7*(1-P7) | R7: =M7+IF($B$3="Amortised",0,L7) | S7: =B7*R7 | T7: =B7*Q7
A8: Delivery vans | B8: 14 | C8: OBD | D8: Y | E8: N | F8: Y | G8: N | H8: N | I8: Basic | J8: =IF(B8=0,0,'Cost Inputs'!$B$5+'Cost Inputs'!$B$14+'Cost Inputs'!$B$15+IF(C8="CAN",'Cost Inputs'!$B$6,IF(C8="OBD",'Cost Inputs'!$B$7,IF(C8="Probe",'Cost Inputs'!$B$8,0)))+IF(D8="Y",'Cost Inputs'!$B$9,0)+IF(E8="Y",'Cost Inputs'!$B$10,0)+IF(F8="Y",'Cost Inputs'!$B$11,0)+IF(G8="Y",'Cost Inputs'!$B$12,0)+IF(H8="Y",'Cost Inputs'!$B$13,0)) | K8: =IF(I8="Basic",'Cost Inputs'!$B$18,IF(I8="Standard",'Cost Inputs'!$B$19,IF(I8="Advanced",'Cost Inputs'!$B$20,0))) | L8: =J8*(1+'Cost Inputs'!$B$36) | M8: =K8*(1+'Cost Inputs'!$B$37) | N8: =SUM('Cost Inputs'!$B$26:$B$32) | O8: =N8/(1-'Cost Inputs'!$B$35)+IF($B$3="Amortised",L8/$F$3,0) | P8: =$K$4 | Q8: =O8*(1-P8) | R8: =M8+IF($B$3="Amortised",0,L8) | S8: =B8*R8 | T8: =B8*Q8
A9: Reefer trucks | B9: 4 | C9: CAN | D9: Y | E9: Y | F9: Y | G9: Y | H9: Y | I9: Advanced | J9: =IF(B9=0,0,'Cost Inputs'!$B$5+'Cost Inputs'!$B$14+'Cost Inputs'!$B$15+IF(C9="CAN",'Cost Inputs'!$B$6,IF(C9="OBD",'Cost Inputs'!$B$7,IF(C9="Probe",'Cost Inputs'!$B$8,0)))+IF(D9="Y",'Cost Inputs'!$B$9,0)+IF(E9="Y",'Cost Inputs'!$B$10,0)+IF(F9="Y",'Cost Inputs'!$B$11,0)+IF(G9="Y",'Cost Inputs'!$B$12,0)+IF(H9="Y",'Cost Inputs'!$B$13,0)) | K9: =IF(I9="Basic",'Cost Inputs'!$B$18,IF(I9="Standard",'Cost Inputs'!$B$19,IF(I9="Advanced",'Cost Inputs'!$B$20,0))) | L9: =J9*(1+'Cost Inputs'!$B$36) | M9: =K9*(1+'Cost Inputs'!$B$37) | N9: =SUM('Cost Inputs'!$B$26:$B$32) | O9: =N9/(1-'Cost Inputs'!$B$35)+IF($B$3="Amortised",L9/$F$3,0) | P9: =$K$4 | Q9: =O9*(1-P9) | R9: =M9+IF($B$3="Amortised",0,L9) | S9: =B9*R9 | T9: =B9*Q9
C10: None | D10: N | E10: N | F10: N | G10: N | H10: N | I10: Basic | J10: =IF(B10=0,0,'Cost Inputs'!$B$5+'Cost Inputs'!$B$14+'Cost Inputs'!$B$15+IF(C10="CAN",'Cost Inputs'!$B$6,IF(C10="OBD",'Cost Inputs'!$B$7,IF(C10="Probe",'Cost Inputs'!$B$8,0)))+IF(D10="Y",'Cost Inputs'!$B$9,0)+IF(E10="Y",'Cost Inputs'!$B$10,0)+IF(F10="Y",'Cost Inputs'!$B$11,0)+IF(G10="Y",'Cost Inputs'!$B$12,0)+IF(H10="Y",'Cost Inputs'!$B$13,0)) | K10: =IF(I10="Basic",'Cost Inputs'!$B$18,IF(I10="Standard",'Cost Inputs'!$B$19,IF(I10="Advanced",'Cost Inputs'!$B$20,0))) | L10: =J10*(1+'Cost Inputs'!$B$36) | M10: =K10*(1+'Cost Inputs'!$B$37) | N10: =SUM('Cost Inputs'!$B$26:$B$32) | O10: =N10/(1-'Cost Inputs'!$B$35)+IF($B$3="Amortised",L10/$F$3,0) | P10: =$K$4 | Q10: =O10*(1-P10) | R10: =M10+IF($B$3="Amortised",0,L10) | S10: =B10*R10 | T10: =B10*Q10
C11: None | D11: N | E11: N | F11: N | G11: N | H11: N | I11: Basic | J11: =IF(B11=0,0,'Cost Inputs'!$B$5+'Cost Inputs'!$B$14+'Cost Inputs'!$B$15+IF(C11="CAN",'Cost Inputs'!$B$6,IF(C11="OBD",'Cost Inputs'!$B$7,IF(C11="Probe",'Cost Inputs'!$B$8,0)))+IF(D11="Y",'Cost Inputs'!$B$9,0)+IF(E11="Y",'Cost Inputs'!$B$10,0)+IF(F11="Y",'Cost Inputs'!$B$11,0)+IF(G11="Y",'Cost Inputs'!$B$12,0)+IF(H11="Y",'Cost Inputs'!$B$13,0)) | K11: =IF(I11="Basic",'Cost Inputs'!$B$18,IF(I11="Standard",'Cost Inputs'!$B$19,IF(I11="Advanced",'Cost Inputs'!$B$20,0))) | L11: =J11*(1+'Cost Inputs'!$B$36) | M11: =K11*(1+'Cost Inputs'!$B$37) | N11: =SUM('Cost Inputs'!$B$26:$B$32) | O11: =N11/(1-'Cost Inputs'!$B$35)+IF($B$3="Amortised",L11/$F$3,0) | P11: =$K$4 | Q11: =O11*(1-P11) | R11: =M11+IF($B$3="Amortised",0,L11) | S11: =B11*R11 | T11: =B11*Q11
C12: None | D12: N | E12: N | F12: N | G12: N | H12: N | I12: Basic | J12: =IF(B12=0,0,'Cost Inputs'!$B$5+'Cost Inputs'!$B$14+'Cost Inputs'!$B$15+IF(C12="CAN",'Cost Inputs'!$B$6,IF(C12="OBD",'Cost Inputs'!$B$7,IF(C12="Probe",'Cost Inputs'!$B$8,0)))+IF(D12="Y",'Cost Inputs'!$B$9,0)+IF(E12="Y",'Cost Inputs'!$B$10,0)+IF(F12="Y",'Cost Inputs'!$B$11,0)+IF(G12="Y",'Cost Inputs'!$B$12,0)+IF(H12="Y",'Cost Inputs'!$B$13,0)) | K12: =IF(I12="Basic",'Cost Inputs'!$B$18,IF(I12="Standard",'Cost Inputs'!$B$19,IF(I12="Advanced",'Cost Inputs'!$B$20,0))) | L12: =J12*(1+'Cost Inputs'!$B$36) | M12: =K12*(1+'Cost Inputs'!$B$37) | N12: =SUM('Cost Inputs'!$B$26:$B$32) | O12: =N12/(1-'Cost Inputs'!$B$35)+IF($B$3="Amortised",L12/$F$3,0) | P12: =$K$4 | Q12: =O12*(1-P12) | R12: =M12+IF($B$3="Amortised",0,L12) | S12: =B12*R12 | T12: =B12*Q12
A14: QUOTE SUMMARY
A15: Total units | C15: =B4
A16: Hardware + installation (once-off) | C16: =SUM(S7:S12)
A17: Account initiation fee | C17: ='Cost Inputs'!B23
A18: TOTAL ONCE-OFF | C18: =C16+C17
A19: Total monthly subscription | C19: =SUM(T7:T12)
A20: Average monthly per unit | C20: =IF(C15=0,0,C19/C15)
A21: Contract term (months) | C21: =F3
A22: CONTRACT TOTAL VALUE (TCV) | C22: =C18+C19*C21

Sheet Tier Pricing
A1: myTrack — Tier Reference Rate Card
A2: Indicative pricing for a STANDARD config (FMB tracker + CAN + panic button, standard install). Driven live from Cost Inputs.
A4: Reference config — per unit
A5: Hardware cost | B5: ='Cost Inputs'!B5+'Cost Inputs'!B14+'Cost Inputs'!B15+'Cost Inputs'!B6+'Cost Inputs'!B9
A6: Hardware price (with markup) | B6: =B5*(1+'Cost Inputs'!B36)
A7: Install price (Standard) | B7: ='Cost Inputs'!B19*(1+'Cost Inputs'!B37)
A8: Monthly run cost | B8: =SUM('Cost Inputs'!B26:B32)
A9: Base monthly price (pre-discount) | B9: =B8/(1-'Cost Inputs'!B35)
A10: Contract term (months) | B10: ='Cost Inputs'!B38
A12: Tier | B12: Fleet size | C12: Once-off / unit (upfront HW) | D12: Monthly / unit (HW upfront) | E12: Monthly / unit (HW amortised)
A13: Small | B13: 5 – 20 units | C13: =$B$6+$B$7 | D13: =$B$9*(1-'Cost Inputs'!B39) | E13: =($B$9+$B$6/$B$10)*(1-'Cost Inputs'!B39)
A14: Medium | B14: 21 – 100 units | C14: =$B$6+$B$7 | D14: =$B$9*(1-'Cost Inputs'!B40) | E14: =($B$9+$B$6/$B$10)*(1-'Cost Inputs'!B40)
A15: Enterprise | B15: 100+ units | C15: =$B$6+$B$7 | D15: =$B$9*(1-'Cost Inputs'!B41) | E15: =($B$9+$B$6/$B$10)*(1-'Cost Inputs'!B41)
A17: Discounts are set per tier in Cost Inputs (section D). Amortised column folds hardware into the monthly fee over the contract term.

Sheet Quote Summary
B2: myTrack — Subscription Proposal
B3: Know where your fleet is. Always.
B5: Prepared for: | C5: [Client name]
B6: Date: | C6: [dd/mm/yyyy]
B7: Prepared by: | C7: [Consultant]
B9: Your proposal
B10: Fleet size (units) | C10: ='Quote Builder'!C15
B11: Contract term (months) | C11: ='Quote Builder'!C21
B13: Once-off (set-up)
B14: Hardware + installation | C14: ='Quote Builder'!C16
B15: Account initiation fee | C15: ='Quote Builder'!C17
B16: Total once-off | C16: ='Quote Builder'!C18
B18: Monthly subscription
B19: Average per unit / month | C19: ='Quote Builder'!C20
B20: Total monthly | C20: ='Quote Builder'!C19
B22: Contract total value
B23: TCV (once-off + monthly × term) | C23: ='Quote Builder'!C22
B25: Pricing indicative and subject to site survey. Valid 30 days. E&OE.
